Metadata-Version: 2.1
Name: PubChem-Prospector
Version: 0.1.2
Summary: functions for bulk scraping pubchem annotations
Home-page: https://github.com/demontrees/PubChem_Prospector
Author: demontrees
Author-email: demontrees96@gmail.com
Classifier: Development Status :: 4 - Beta
Classifier: Intended Audience :: Developers
Classifier: License :: OSI Approved :: GNU General Public License v3 (GPLv3)
Classifier: Programming Language :: Python :: 3
Classifier: Programming Language :: Python :: 3.9
Requires-Python: >=3.6
License-File: LICENSE
